setup.py
markovjson/__init__.py
markovjson/mkov.py
markovjson/nlp.py
markovjson/tokenizers.py
markovjson/topic_modelling.py
markovjson.egg-info/PKG-INFO
markovjson.egg-info/SOURCES.txt
markovjson.egg-info/dependency_links.txt
markovjson.egg-info/requires.txt
markovjson.egg-info/top_level.txt