Metadata-Version: 1.0
Name: markovjson
Version: 0.1.0
Summary: json meets markov chains
Home-page: https://github.com/OpenJarbas/markovjson
Author: jarbasAi
Author-email: jarbasai@mailfence.com
License: apache-2
Platform: UNKNOWN
